ChangeLog
LICENSE
MANIFEST.in
README.rst
setup.py
bin/django-gitcms-load-content
django_gitcms.egg-info/PKG-INFO
django_gitcms.egg-info/SOURCES.txt
django_gitcms.egg-info/dependency_links.txt
django_gitcms.egg-info/top_level.txt
example-website/README
example-website/__init__.py
example-website/manage.py
example-website/settings.py
example-website/urls.py
example-website/content/blog/firstpost.rst
example-website/content/files/Luis_Pedro_Coelho.vcf
example-website/content/files/arrows.png
example-website/content/files/mississippi-0-no-sl.png
example-website/content/files/mississippi-0.png
example-website/content/files/niagara-small.jpg
example-website/content/files/painting-rice.jpeg
example-website/content/menus/menu.yaml
example-website/content/menus/top.yaml
example-website/content/pages/another
example-website/content/pages/gitcms
example-website/content/pages/index
example-website/content/pages/template
example-website/content/redirect/one2two_three2four.yaml
example-website/content/tagging/tags
example-website/media/.gitignore
example-website/media/images/ramblingsoul3/footer.png
example-website/media/images/ramblingsoul3/headbanner.png
example-website/media/images/ramblingsoul3/header-bg.png
example-website/media/images/ramblingsoul3/highlightgreen.png
example-website/media/images/ramblingsoul3/logo.png
example-website/media/images/ramblingsoul3/menu-hvr.png
example-website/media/images/ramblingsoul3/menu.png
example-website/media/images/ramblingsoul3/topheadbg.png
example-website/media/js/jquery.js
example-website/media/style/luispedro.css
example-website/media/style/ramblingsoul3.css
example-website/media/style/rest.css
example-website/templates/base.html
gitcms/__init__.py
gitcms/gitcms_version.py
gitcms/blog/__init__.py
gitcms/blog/admin.py
gitcms/blog/feeds.py
gitcms/blog/load.py
gitcms/blog/models.py
gitcms/blog/urls.py
gitcms/blog/views.py
gitcms/blog/templates/blog/article.html
gitcms/blog/templates/blog/disqus.html
gitcms/blog/templates/blog/list.html
gitcms/blog/templates/blog/post.html
gitcms/blog/templatetags/__init__.py
gitcms/blog/templatetags/disqus.py
gitcms/books/__init__.py
